setup.py
MySerializer/MySerializer.py
MySerializer/__init__.py
MySerializer/constants.py
MySerializer/json_utils.py
MySerializer/pack_utils.py
MySerializer/serializer.py
MySerializer/unpack_utils.py
MySerializer/xml_utils.py
denvilk_serializer.egg-info/PKG-INFO
denvilk_serializer.egg-info/SOURCES.txt
denvilk_serializer.egg-info/dependency_links.txt
denvilk_serializer.egg-info/entry_points.txt
denvilk_serializer.egg-info/top_level.txt
tests/test_attributes.py