Metadata-Version: 2.1
Name: denvilk-serializer
Version: 1.0.0
Summary: JSON and XLM serializer
Author: Vladimir Velikovich
Author-email: vvelikovich@gmail.com
